travel_pricing_scraper/__init__.py
travel_pricing_scraper/cli.py
travel_pricing_scraper/flights.py
travel_pricing_scraper/models.py
travel_pricing_scraper/scrapers/__init__.py
travel_pricing_scraper/scrapers/flights/__init__.py
travel_pricing_scraper/scrapers/flights/decolar.py
travel_pricing_scraper/utils/__init__.py
travel_pricing_scraper-0.1.2.dist-info/LICENSE
travel_pricing_scraper-0.1.2.dist-info/METADATA
travel_pricing_scraper-0.1.2.dist-info/WHEEL
travel_pricing_scraper-0.1.2.dist-info/entry_points.txt
travel_pricing_scraper-0.1.2.dist-info/RECORD
