Metadata-Version: 2.1
Name: travel-pricing-scraper
Version: 0.1.2
Summary: In this project, Playwright is used to navigate through different airline websites, fill in search forms, click buttons, and extract price information. 
License: Beerware
Author: Kalel L. Martinho
Author-email: kalel@tutamail.com
Requires-Python: >=3.10,<4.0
Classifier: Development Status :: 5 - Production/Stable
Classifier: Environment :: Console
Classifier: License :: Other/Proprietary License
Classifier: Programming Language :: Python :: 3
Classifier: Programming Language :: Python :: 3.10
Classifier: Programming Language :: Python :: 3.11
Classifier: Topic :: Education
Requires-Dist: airportsdata (>=20230617,<20230618)
Requires-Dist: playwright (>=1.35.0,<2.0.0)
Requires-Dist: pydantic (>=1.10.9,<2.0.0)
Requires-Dist: python-dateutil (>=2.8.2,<3.0.0)
Requires-Dist: rich (>=13.4.2,<14.0.0)
Requires-Dist: typer (>=0.9.0,<0.10.0)
Project-URL: Bug Tracker, https://github.com/kalelmartinho/travel-pricing-scraper/issues
Project-URL: Code, https://github.com/kalelmartinho/travel-pricing-scraper
Project-URL: Docs, https://travel-pricing-scraper.readthedocs.io/en/latest/
